bigquery_orm/__init__.py
bigquery_orm-0.0.1.dist-info/LICENSE
bigquery_orm-0.0.1.dist-info/METADATA
bigquery_orm-0.0.1.dist-info/WHEEL
bigquery_orm-0.0.1.dist-info/top_level.txt
bigquery_orm-0.0.1.dist-info/zip-safe
bigquery_orm-0.0.1.dist-info/RECORD
