Metadata-Version: 2.1
Name: bigquery-orm
Version: 0.0.1
Summary: BigQuery ORM
Home-page: https://github.com/FernandoCelmer/python-bigquery-orm
Author: Fernando Celmer
Author-email: email@fernandocelmer.com
Classifier: Development Status :: 4 - Beta
Classifier: Operating System :: OS Independent
Classifier: License :: OSI Approved :: MIT License
Classifier: Intended Audience :: Developers
Classifier: Natural Language :: English
Classifier: Programming Language :: Python :: 3.6
Classifier: Programming Language :: Python :: 3.7
Classifier: Programming Language :: Python :: 3.8
Classifier: Programming Language :: Python :: 3.9
Classifier: Programming Language :: Python :: 3.10
Classifier: Programming Language :: Python :: 3.11
Requires-Python: >=3.6
License-File: LICENSE
